odoo8_addon_crm_lead_second_lastname-8.0.1.0.0.99.dev11-py3.8-nspkg.pth
odoo_addons/crm_lead_second_lastname/README.rst
odoo_addons/crm_lead_second_lastname/__init__.py
odoo_addons/crm_lead_second_lastname/__openerp__.py
odoo_addons/crm_lead_second_lastname/i18n/bg.po
odoo_addons/crm_lead_second_lastname/i18n/crm_lead_second_lastname.pot
odoo_addons/crm_lead_second_lastname/i18n/de.po
odoo_addons/crm_lead_second_lastname/i18n/es.po
odoo_addons/crm_lead_second_lastname/i18n/fr.po
odoo_addons/crm_lead_second_lastname/i18n/hr.po
odoo_addons/crm_lead_second_lastname/i18n/it.po
odoo_addons/crm_lead_second_lastname/i18n/pt_BR.po
odoo_addons/crm_lead_second_lastname/i18n/sk.po
odoo_addons/crm_lead_second_lastname/i18n/sl.po
odoo_addons/crm_lead_second_lastname/i18n/zh_CN.po
odoo_addons/crm_lead_second_lastname/models/__init__.py
odoo_addons/crm_lead_second_lastname/models/crm_lead.py
odoo_addons/crm_lead_second_lastname/static/description/icon.png
odoo_addons/crm_lead_second_lastname/tests/__init__.py
odoo_addons/crm_lead_second_lastname/tests/test_crm_lead.py
odoo_addons/crm_lead_second_lastname/views/crm_lead_view.xml
odoo8_addon_crm_lead_second_lastname-8.0.1.0.0.99.dev11.dist-info/METADATA
odoo8_addon_crm_lead_second_lastname-8.0.1.0.0.99.dev11.dist-info/WHEEL
odoo8_addon_crm_lead_second_lastname-8.0.1.0.0.99.dev11.dist-info/namespace_packages.txt
odoo8_addon_crm_lead_second_lastname-8.0.1.0.0.99.dev11.dist-info/top_level.txt
odoo8_addon_crm_lead_second_lastname-8.0.1.0.0.99.dev11.dist-info/RECORD
